testing/__init__.py
testing/postgresql.py
testing.postgresql-1.2.1.dist-info/DESCRIPTION.rst
testing.postgresql-1.2.1.dist-info/METADATA
testing.postgresql-1.2.1.dist-info/metadata.json
testing.postgresql-1.2.1.dist-info/RECORD
testing.postgresql-1.2.1.dist-info/top_level.txt
testing.postgresql-1.2.1.dist-info/WHEEL
