Metadata-Version: 2.0
Name: testing.postgresql
Version: 1.2.1
Summary: automatically setups a postgresql instance in a temporary "         "directory, and destroys it after testing
Home-page: https://github.com/tk0miya/testing.postgresql
Author: Takeshi Komiya
Author-email: i.tkomiya at gmail.com
License: Apache License 2.0
Platform: UNKNOWN
Classifier: Development Status :: 4 - Beta
Classifier: Intended Audience :: Developers
Classifier: License :: OSI Approved :: Apache Software License
Classifier: Programming Language :: Python
Classifier: Programming Language :: Python :: 2.6
Classifier: Programming Language :: Python :: 2.7
Classifier: Programming Language :: Python :: 3.2
Classifier: Programming Language :: Python :: 3.3
Classifier: Topic :: Database
Classifier: Topic :: Software Development
Classifier: Topic :: Software Development :: Testing
Requires-Dist: pg8000 (>=1.10)
Provides-Extra: testing
Requires-Dist: nose; extra == 'testing'
Requires-Dist: psycopg2; extra == 'testing'
Requires-Dist: SQLAlchemy; extra == 'testing'
